auf/__init__.py
auf/constants/__init__.py
auf/constants/metrics.py
auf/constants/models.py
auf/data/__init__.py
auf/data/checks.py
auf/data/preprocessing.py
auf/data/split.py
auf/feature_rankers/__init__.py
auf/feature_rankers/filter.py
auf/feature_rankers/importance.py
auf/feature_rankers/permutation.py
auf/feature_rankers/stepwise.py
auf/feature_rankers/straightforward.py
auf/metrics/__init__.py
auf/metrics/averaged.py
auf/metrics/by_top.py
auf/metrics/overfit.py
auf/ml_flow/__init__.py
auf/ml_flow/ml_flow.py
auf/models/__init__.py
auf/models/auf_forest.py
auf/models/auf_s_learner.py
auf/models/auf_tree.py
auf/models/auf_x_learner.py
auf/pipeline/__init__.py
auf/pipeline/binary.py
auf/pipeline/calibration.py
auf/pipeline/inference.py
auf/plots/__init__.py
auf/plots/plots.py
auf/training/__init__.py
auf/training/fitting.py
auf/training/gridsearch.py
auf-1.0.0.dist-info/LICENSE
auf-1.0.0.dist-info/METADATA
auf-1.0.0.dist-info/WHEEL
auf-1.0.0.dist-info/top_level.txt
auf-1.0.0.dist-info/RECORD
